LICENSE
README.md
setup.py
botmail/__init__.py
botmail/webmail.py
botmail.egg-info/PKG-INFO
botmail.egg-info/SOURCES.txt
botmail.egg-info/dependency_links.txt
botmail.egg-info/top_level.txt