Metadata-Version: 2.4
Name: botmail
Version: 0.2.7
Summary: Class to handle smpt and imap server for RPA apps
Home-page: https://github.com/botlorien/botmail
Author: Ben-Hur P. B. Santos
Author-email: botlorien@gmail.com
Classifier: Programming Language :: Python :: 3
Classifier: License :: OSI Approved :: MIT License
Classifier: Operating System :: OS Independent
Requires-Python: >=3.10
License-File: LICENSE
Dynamic: author
Dynamic: author-email
Dynamic: classifier
Dynamic: description
Dynamic: description-content-type
Dynamic: home-page
Dynamic: license-file
Dynamic: requires-python
Dynamic: summary
